{"name": "20220303102517", "proxyPass": "", "proxyUser": "", "proxyPort": "", "proxyHost": "", "proxyType": "HTTP", "proxyServer": {"setProxyServer": false, "type": "HTTP", "password": "", "username": "", "port": "", "host": ""}, "tag": "", "notes": "", "userAgent": "Mozilla/5.0 (Windows NT 6.3; Win64; x64) AppleWebKit/537.36 (KHTML, like Gecko) Chrome/86.0.4240.193 Safari/537.36", "uaCoreFollow": false, "canvasDefType": "NOISE", "maskFonts": true, "platform": "Win32", "langHdr": "es-AR", "screenHeight": 960, "screenWidth": 1280, "timeZoneFillOnStart": false, "timeZone": "Asia/Shanghai", "startUrl": "about:blank", "kernelVer": "96", "audio": {"noise": true}, "mediaDevices": {"setMediaDevices": true, "use_name": false, "list": {"videoInputs": {"device1": {"label": "n/a", "deviceId": "n/a", "groupId": "70fa02ce8dfd85963dfda7f475b183aa11b18f8f352509a77386c442571cd369"}}, "audioInputs": {"device1": {"label": "n/a", "deviceId": "n/a", "groupId": "500083b6171104f7d8be9073e9470ff3bcf979f045994122feb2cef7a616acf0"}, "device2": {"label": "n/a", "deviceId": "n/a", "groupId": "f0c27af2627326d44d8290b764d5cf4fcfbc1c302405c6ed510a9b736b04df09"}, "device3": {"label": "n/a", "deviceId": "n/a", "groupId": "dd281aa87b6c05811da920e83b7210f70adbfd507ec113ee74be8013372b2d07"}}, "audioOutputs": []}, "videoInputs": 1, "audioInputs": 3, "audioOutputs": 0}, "webgl": {"noise": true, "vendor": "Google Inc. (AMD)", "renderer": "ANGLE (AMD, Radeon RX 550X Direct3D11 vs_5_0 ps_5_0, D3D11-27.20.14501.28009)", "imgProtect": true}, "webRtc": {"type": "FAKE", "fillOnStart": true, "wanSet": true, "lanSet": true, "publicIp": "224.162.109.180", "localIps": ["172.16.122.76"]}, "browserSettings": {"pepperFlash": false, "mediaStream": true, "webkitSpeech": true, "fakeUiForMedia": true, "gpuAndPepper3D": false, "ignoreCertErrors": false, "audioMute": false, "disableWebSecurity": false, "disablePdf": false, "touchEvents": false, "hyperlinkAuditing": true}, "localCache": {"deleteCache": false, "deleteCookie": false, "clearCache": false, "clearHistory": false}, "synSettings": {"synCookie": true, "synBookmark": true, "synHistory": true, "synExtension": false, "synKeepKey": true, "synLastTag": true}, "leakProof": {"computerName": "PC-BJW2YZQG2I", "macAddress": "CC-F4-11-10-02-0C"}, "browserParams": "", "customDns": "", "remoteDebug": {"bindAllDebug": false, "debuggingPort": 0, "logLevels": 99}, "pluginFingerprint": {"pluginEnable": false, "list": {"name": [], "describe": [], "fileName": [], "mimeType": [], "mimeDescription": [], "mimeExtension": []}}, "unPluginFingerprint": {"list": {"name": [], "describe": [], "fileName": [], "mimeType": [], "mimeDescription": [], "mimeExtension": []}}, "browserApi": {"isCharging": true, "setBatteryStatus": false, "autoGeoIp": true, "setLatitude": false, "setLongitude": false, "setAccuracy": false, "setWebBluetooth": false, "setBluetoothAdapter": false, "speechSynthesis": false, "chargingTime": "0", "drainsTime": "Infinity", "batteryPercentage": "1", "latitude": "51.482594", "longitude": "-0.007661", "accuracy": "1803.34", "voiceURI": [], "name": [], "lang": [], "localService": [], "default": []}, "sslFingerprint": {"enableCustomSSL": false, "versionMin": 0, "versionMax": 1, "cipherSuites": {"TLS_AES_128_GCM_SHA256": true, "TLS_AES_256_GCM_SHA384": true, "TLS_CHACHA20_POLY1305_SHA256": true, "TLS_ECDHE_ECDSA_WITH_AES_128_GCM_SHA256": true, "TLS_ECDHE_RSA_WITH_AES_128_GCM_SHA256": true, "TLS_ECDHE_ECDSA_WITH_AES_256_GCM_SHA384": true, "TLS_ECDHE_RSA_WITH_AES_256_GCM_SHA384": true, "TLS_ECDHE_ECDSA_WITH_CHACHA20_POLY1305_SHA256": true, "TLS_ECDHE_RSA_WITH_CHACHA20_POLY1305_SHA256": true, "TLS_ECDHE_RSA_WITH_AES_128_CBC_SHA": true, "TLS_ECDHE_RSA_WITH_AES_256_CBC_SHA": true, "TLS_RSA_WITH_AES_128_GCM_SHA256": true, "TLS_RSA_WITH_AES_256_GCM_SHA384": true, "TLS_RSA_WITH_AES_128_CBC_SHA": true, "TLS_RSA_WITH_AES_256_CBC_SHA": true, "TLS_RSA_WITH_3DES_EDE_CBC_SHA": false, "TLS_ECDHE_ECDSA_WITH_AES_128_CBC_SHA": false}}, "otherProtection": {"setPortScan": true, "localPortsExclude": ""}, "header": {"setHeaderCustom": false, "list": {"enable": [], "name": [], "value": [], "urlMatch": [], "notExistAdd": []}}, "cmdcfg": {"openCommandLine": false, "commandLine": "", "closeCommandLine": true}, "acceptLanguage": "es-AR,es;q=0.9", "hardwareConcurrency": 4, "dynamicFonts": true, "fontList": [], "clientRects": true, "fontSetting": {"dynamicFonts": true, "fontList": [], "clientRects": true}, "doNotTrack": false, "hideWebdriver": false, "langBasedOnIp": true, "deviceMemory": 8, "product": "Gecko", "appName": "Netscape", "iconId": 0, "mobileEmulation": false, "deviceType": 0, "pixelRatio": "1.0", "os": "Windows"}